README.rst
setup.cfg
setup.py
oaas_grpc_compiler/__init__.py
oaas_grpc_compiler/mainapp.py
oaas_grpc_compiler/py.typed
oaas_grpc_compiler.egg-info/PKG-INFO
oaas_grpc_compiler.egg-info/SOURCES.txt
oaas_grpc_compiler.egg-info/dependency_links.txt
oaas_grpc_compiler.egg-info/entry_points.txt
oaas_grpc_compiler.egg-info/requires.txt
oaas_grpc_compiler.egg-info/top_level.txt