Metadata-Version: 1.0
Name: oaas-grpc-compiler
Version: 1.0.1
Summary: oaas_grpc_compiler
Home-page: UNKNOWN
Author: Bogdan Mustiata
Author-email: bogdan.mustiata@gmail.com
License: BSD
Platform: UNKNOWN
